h2o_wave_university/__init__.py
h2o_wave_university/cli.py
h2o_wave_university/university.py
h2o_wave_university/utils.py
h2o_wave_university/version.py
h2o_wave_university/autocomplete_parser.py
h2o_wave_university/autocomplete_utils.py
h2o_wave_university-1.7.7.data/data/h2o_wave_university/lessons/lesson1.py
h2o_wave_university-1.7.7.data/data/h2o_wave_university/lessons/lesson10.py
h2o_wave_university-1.7.7.data/data/h2o_wave_university/lessons/lesson11.py
h2o_wave_university-1.7.7.data/data/h2o_wave_university/lessons/lesson12.py
h2o_wave_university-1.7.7.data/data/h2o_wave_university/lessons/lesson13.py
h2o_wave_university-1.7.7.data/data/h2o_wave_university/lessons/lesson2.py
h2o_wave_university-1.7.7.data/data/h2o_wave_university/lessons/lesson3.py
h2o_wave_university-1.7.7.data/data/h2o_wave_university/lessons/lesson4.py
h2o_wave_university-1.7.7.data/data/h2o_wave_university/lessons/lesson5.py
h2o_wave_university-1.7.7.data/data/h2o_wave_university/lessons/lesson6.py
h2o_wave_university-1.7.7.data/data/h2o_wave_university/lessons/lesson7.py
h2o_wave_university-1.7.7.data/data/h2o_wave_university/lessons/lesson8.py
h2o_wave_university-1.7.7.data/data/h2o_wave_university/lessons/lesson9.py
h2o_wave_university-1.7.7.data/data/h2o_wave_university/static/h2o-logo.svg
h2o_wave_university-1.7.7.data/data/h2o_wave_university/static/loader.min.js
h2o_wave_university-1.7.7.data/data/h2o_wave_university/static/university.js
h2o_wave_university-1.7.7.data/data/h2o_wave_university/static/monaco/base/browser/ui/codicons/codicon/codicon.ttf
h2o_wave_university-1.7.7.data/data/h2o_wave_university/static/monaco/base/worker/workerMain.js
h2o_wave_university-1.7.7.data/data/h2o_wave_university/static/monaco/basic-languages/python/python.js
h2o_wave_university-1.7.7.data/data/h2o_wave_university/static/monaco/editor/editor.main.css
h2o_wave_university-1.7.7.data/data/h2o_wave_university/static/monaco/editor/editor.main.js
h2o_wave_university-1.7.7.dist-info/METADATA
h2o_wave_university-1.7.7.dist-info/WHEEL
h2o_wave_university-1.7.7.dist-info/entry_points.txt
h2o_wave_university-1.7.7.dist-info/licenses/LICENSE
h2o_wave_university-1.7.7.dist-info/RECORD
